functionhub/__init__.py
functionhub/config.ini
functionhub/main.py
test/__init__.py
test/test_main.py
functionhub-0.2.3.dist-info/LICENSE
functionhub-0.2.3.dist-info/METADATA
functionhub-0.2.3.dist-info/WHEEL
functionhub-0.2.3.dist-info/entry_points.txt
functionhub-0.2.3.dist-info/top_level.txt
functionhub-0.2.3.dist-info/RECORD
