Metadata-Version: 2.1
Name: functionhub
Version: 0.2.3
Summary: A client for CloudStash.io interaction
Home-page: https://cloudstash.io
Author: naesheim
License: UNKNOWN
Platform: UNKNOWN
Classifier: Programming Language :: Python :: 3
Classifier: License :: OSI Approved :: MIT License
Classifier: Operating System :: OS Independent
Requires-Python: >=3.6
Requires-Dist: Click
Requires-Dist: requests
Requires-Dist: chardet
Requires-Dist: urllib3
